ZIP96Pico.py
KitronikPicoZIP96-1.0.2.dist-info/LICENSE
KitronikPicoZIP96-1.0.2.dist-info/METADATA
KitronikPicoZIP96-1.0.2.dist-info/WHEEL
KitronikPicoZIP96-1.0.2.dist-info/top_level.txt
KitronikPicoZIP96-1.0.2.dist-info/RECORD
