Metadata-Version: 2.1
Name: KitronikPicoZIP96
Version: 1.0.2
Summary: Kitronik Pico ZIP96 a complete controller with LED screen
License-File: LICENSE
